{
"type": "FeatureCollection",
"name": "緑ケ丘",
"crs": { "type": "name", "properties": { "name": "urn:ogc:def:crs:EPSG::4612" } },
"features": [
{ "type": "Feature", "properties": { "供用済面積": 1537, "供用開始年": 1975, "公園名": "緑ケ丘南公園", "公園種別": "街区公園", "所在地市区町村名": "厚木市", "所在地都道府県名": "神奈川県", "管理市区町村": "厚木市", "管理都道府県・整備局": "神奈川県", "都市計画決定": 2, "TOWN": "緑ケ丘" }, "geometry": { "type": "Point", "coordinates": [ 139.34402745, 35.45101827 ] } },
{ "type": "Feature", "properties": { "供用済面積": 701, "供用開始年": 1975, "公園名": "緑ケ丘北公園", "公園種別": "街区公園", "所在地市区町村名": "厚木市", "所在地都道府県名": "神奈川県", "管理市区町村": "厚木市", "管理都道府県・整備局": "神奈川県", "都市計画決定": 2, "TOWN": "緑ケ丘" }, "geometry": { "type": "Point", "coordinates": [ 139.343887849999987, 35.45379359 ] } },
{ "type": "Feature", "properties": { "供用済面積": 1945, "供用開始年": 1975, "公園名": "緑ケ丘西公園", "公園種別": "街区公園", "所在地市区町村名": "厚木市", "所在地都道府県名": "神奈川県", "管理市区町村": "厚木市", "管理都道府県・整備局": "神奈川県", "都市計画決定": 2, "TOWN": "緑ケ丘" }, "geometry": { "type": "Point", "coordinates": [ 139.339829220000013, 35.45248395 ] } },
{ "type": "Feature", "properties": { "供用済面積": 837, "供用開始年": 1975, "公園名": "緑ケ丘やなぎ公園", "公園種別": "街区公園", "所在地市区町村名": "厚木市", "所在地都道府県名": "神奈川県", "管理市区町村": "厚木市", "管理都道府県・整備局": "神奈川県", "都市計画決定": 2, "TOWN": "緑ケ丘" }, "geometry": { "type": "Point", "coordinates": [ 139.33962926, 35.45374581 ] } },
{ "type": "Feature", "properties": { "供用済面積": 1650, "供用開始年": 1975, "公園名": "緑ケ丘まる公園", "公園種別": "街区公園", "所在地市区町村名": "厚木市", "所在地都道府県名": "神奈川県", "管理市区町村": "厚木市", "管理都道府県・整備局": "神奈川県", "都市計画決定": 2, "TOWN": "緑ケ丘" }, "geometry": { "type": "Point", "coordinates": [ 139.3401, 35.45494 ] } },
{ "type": "Feature", "properties": { "供用済面積": 760, "供用開始年": 1975, "公園名": "緑ケ丘１丁目芝公園", "公園種別": "街区公園", "所在地市区町村名": "厚木市", "所在地都道府県名": "神奈川県", "管理市区町村": "厚木市", "管理都道府県・整備局": "神奈川県", "都市計画決定": 2, "TOWN": "緑ケ丘" }, "geometry": { "type": "Point", "coordinates": [ 139.34284557, 35.45017986 ] } },
{ "type": "Feature", "properties": { "供用済面積": 753, "供用開始年": 1975, "公園名": "緑ケ丘２丁目芝公園", "公園種別": "街区公園", "所在地市区町村名": "厚木市", "所在地都道府県名": "神奈川県", "管理市区町村": "厚木市", "管理都道府県・整備局": "神奈川県", "都市計画決定": 2, "TOWN": "緑ケ丘" }, "geometry": { "type": "Point", "coordinates": [ 139.34200997, 35.4504881 ] } },
{ "type": "Feature", "properties": { "供用済面積": 3976, "供用開始年": 1983, "公園名": "緑ケ丘さくら公園", "公園種別": "街区公園", "所在地市区町村名": "厚木市", "所在地都道府県名": "神奈川県", "管理市区町村": "厚木市", "管理都道府県・整備局": "神奈川県", "都市計画決定": 2, "TOWN": "緑ケ丘" }, "geometry": { "type": "Point", "coordinates": [ 139.34231109000001, 35.45599018 ] } }
]
}
