{
"type": "FeatureCollection",
"name": "船子",
"crs": { "type": "name", "properties": { "name": "urn:ogc:def:crs:EPSG::4612" } },
"features": [
{ "type": "Feature", "properties": { "供用済面積": 1154, "供用開始年": 1983, "公園名": "ひばり公園", "公園種別": "街区公園", "所在地市区町村名": "厚木市", "所在地都道府県名": "神奈川県", "管理市区町村": "厚木市", "管理都道府県・整備局": "神奈川県", "都市計画決定": 2, "TOWN": "船子" }, "geometry": { "type": "Point", "coordinates": [ 139.35455701, 35.43118728 ] } },
{ "type": "Feature", "properties": { "供用済面積": 1799, "供用開始年": 1986, "公園名": "船子長ヶ町公園", "公園種別": "街区公園", "所在地市区町村名": "厚木市", "所在地都道府県名": "神奈川県", "管理市区町村": "厚木市", "管理都道府県・整備局": "神奈川県", "都市計画決定": 2, "TOWN": "船子" }, "geometry": { "type": "Point", "coordinates": [ 139.35662462, 35.4267473 ] } },
{ "type": "Feature", "properties": { "供用済面積": 807, "供用開始年": 1989, "公園名": "船子宮の里公園", "公園種別": "街区公園", "所在地市区町村名": "厚木市", "所在地都道府県名": "神奈川県", "管理市区町村": "厚木市", "管理都道府県・整備局": "神奈川県", "都市計画決定": 2, "TOWN": "船子" }, "geometry": { "type": "Point", "coordinates": [ 139.34950659, 35.42786872 ] } }
]
}
