{
"type": "FeatureCollection",
"name": "上荻野",
"crs": { "type": "name", "properties": { "name": "urn:ogc:def:crs:EPSG::4612" } },
"features": [
{ "type": "Feature", "properties": { "レベル": 1, "住所": "神奈川県厚木市上荻野8", "収容人数": 1000, "名称": "荻野小学校", "施設の種類": "避難所", "施設規模": 5824, "災害分類": "地震・水害", "経度": 139.320812, "緯度": 35.491728, "行政区域": "14212", "高さ": "17.004", "TOWN": "上荻野" }, "geometry": { "type": "Point", "coordinates": [ 139.320812, 35.491728 ] } },
{ "type": "Feature", "properties": { "レベル": 1, "住所": "神奈川県厚木市上荻野1429", "収容人数": 1000, "名称": "上荻野小学校", "施設の種類": "避難所", "施設規模": 5655, "災害分類": "地震・水害", "経度": 139.311785, "緯度": 35.507143, "行政区域": "14212", "高さ": "6.447", "TOWN": "上荻野" }, "geometry": { "type": "Point", "coordinates": [ 139.311785, 35.507143 ] } }
]
}
