{
"type": "FeatureCollection",
"name": "中荻野",
"crs": { "type": "name", "properties": { "name": "urn:ogc:def:crs:EPSG::4612" } },
"features": [
{ "type": "Feature", "properties": { "レベル": 3, "住所": "神奈川県厚木市中荻野1500", "収容人数": 4000, "名称": "荻野運動公園", "施設の種類": "避難所", "施設規模": 11002, "災害分類": "地震・水害", "経度": 139.32252158599999, "緯度": 35.482420507100002, "行政区域": "14212", "高さ": "", "TOWN": "中荻野" }, "geometry": { "type": "Point", "coordinates": [ 139.322521586, 35.482420507 ] } }
]
}
