{
"type": "FeatureCollection",
"name": "恩名",
"crs": { "type": "name", "properties": { "name": "urn:ogc:def:crs:EPSG::4612" } },
"features": [
{ "type": "Feature", "properties": { "レベル": 1, "住所": "神奈川県厚木市恩名2-16-1", "収容人数": 1000, "名称": "南毛利中学校", "施設の種類": "避難所", "施設規模": 8510, "災害分類": "地震・水害", "経度": 139.352337, "緯度": 35.443234, "行政区域": "14212", "高さ": "15.115", "TOWN": "恩名" }, "geometry": { "type": "Point", "coordinates": [ 139.352337, 35.443234 ] } }
]
}
