{
"type": "FeatureCollection",
"name": "王子",
"crs": { "type": "name", "properties": { "name": "urn:ogc:def:crs:EPSG::4612" } },
"features": [
{ "type": "Feature", "properties": { "レベル": 1, "住所": "神奈川県厚木市王子3-1-1", "収容人数": 1500, "名称": "厚木商業高校", "施設の種類": "避難所", "施設規模": 14947, "災害分類": "地震・水害", "経度": 139.342754, "緯度": 35.45726, "行政区域": "14212", "高さ": "20.026", "TOWN": "王子" }, "geometry": { "type": "Point", "coordinates": [ 139.342754, 35.45726 ] } },
{ "type": "Feature", "properties": { "レベル": 1, "住所": "神奈川県厚木市王子1-1-1", "収容人数": 1500, "名称": "厚木東高校", "施設の種類": "避難所", "施設規模": 13572, "災害分類": "地震・水害", "経度": 139.34431, "緯度": 35.456205, "行政区域": "14212", "高さ": "", "TOWN": "王子" }, "geometry": { "type": "Point", "coordinates": [ 139.34431, 35.456205 ] } }
]
}
