{
"type": "FeatureCollection",
"name": "飯山",
"crs": { "type": "name", "properties": { "name": "urn:ogc:def:crs:EPSG::4612" } },
"features": [
{ "type": "Feature", "properties": { "レベル": 1, "住所": "神奈川県厚木市飯山2360", "収容人数": 1000, "名称": "小鮎小学校", "施設の種類": "避難所", "施設規模": 6234, "災害分類": "地震・水害", "経度": 139.322783, "緯度": 35.463064, "行政区域": "14212", "高さ": "", "TOWN": "飯山" }, "geometry": { "type": "Point", "coordinates": [ 139.322783, 35.463064 ] } },
{ "type": "Feature", "properties": { "レベル": 1, "住所": "神奈川県厚木市飯山2367", "収容人数": 700, "名称": "小鮎中学校", "施設の種類": "避難所", "施設規模": 7464, "災害分類": "地震・水害", "経度": 139.323283, "緯度": 35.462064, "行政区域": "14212", "高さ": "", "TOWN": "飯山" }, "geometry": { "type": "Point", "coordinates": [ 139.323283, 35.462064 ] } },
{ "type": "Feature", "properties": { "レベル": 1, "住所": "神奈川県厚木市飯山4400", "収容人数": 1000, "名称": "飯山小学校", "施設の種類": "避難所", "施設規模": 6348, "災害分類": "地震・水害", "経度": 139.320561, "緯度": 35.472535, "行政区域": "14212", "高さ": "18.443", "TOWN": "飯山" }, "geometry": { "type": "Point", "coordinates": [ 139.320561, 35.472535 ] } }
]
}
